topsis_raghavpahwa_102303608/__init__.py
topsis_raghavpahwa_102303608/topsis.py
topsis_raghavpahwa_102303608-1.0.1.dist-info/METADATA
topsis_raghavpahwa_102303608-1.0.1.dist-info/WHEEL
topsis_raghavpahwa_102303608-1.0.1.dist-info/entry_points.txt
topsis_raghavpahwa_102303608-1.0.1.dist-info/top_level.txt
topsis_raghavpahwa_102303608-1.0.1.dist-info/RECORD
