Metadata-Version: 2.4
Name: Topsis-RaghavPahwa-102303608
Version: 1.0.1
Summary: A command-line implementation of TOPSIS
Author: Raghav Pahwa
Author-email: rpahwa_be23@thapar.edu
License: MIT
Requires-Python: >=3.7
Requires-Dist: pandas
Requires-Dist: numpy
Dynamic: author
Dynamic: author-email
Dynamic: description
Dynamic: description-content-type
Dynamic: license
Dynamic: requires-dist
Dynamic: requires-python
Dynamic: summary
